{
  "issue": "C1",
  "description": "Lift map produces demitesseract vs 16-cell vertices",
  "resolution": "TERMINOLOGICAL - demitesseract = 16-cell in different coordinates",
  "mathematical_validity": "UNCHANGED - embedding chain is valid",
  "key_facts": [
    "Demitesseract and 16-cell are the same polytope",
    "Both have 8 vertices, 24 edges, same Weyl group W(B\u2084)",
    "Related by orthogonal transformation (Hadamard matrix)",
    "S\u2084 \u00d7 Z\u2082 \u2192 W(B\u2084) embedding is correct"
  ],
  "action_required": "Clarify terminology in theorem derivation",
  "symmetry_verification": {
    "demitesseract_symmetries": 192,
    "expected_W_B4": 384,
    "match": false
  }
}