{
  "issue_1": {
    "issue": "Soliton Rotation",
    "status": "RESOLVED",
    "justification": "Phase structure rotation, not matter rotation",
    "theorem_support": [
      "Theorem 0.2.3 (stable fixed point)",
      "Theorem 2.2.2 (limit cycle)"
    ],
    "rotation_rate": "3\u00d7 \u03c9_cycle (one rotation per convergence event)"
  },
  "issue_2": {
    "issue": "Missing Citations",
    "status": "RESOLVED",
    "citations": [
      "MIT Bag Model",
      "Chiral Condensate Suppression",
      "String Tension (Lattice QCD)",
      "Bag Constant",
      "Einstein-Cartan Torsion",
      "SU(3) Representation Theory",
      "Sakaguchi-Kuramoto Model",
      "Skyrmion/Soliton Theory"
    ],
    "html_snippet": "\n<!-- REFERENCES SECTION - Add to theory panel -->\n<div class=\"concept\" style=\"margin-top: 25px;\">\n    <div class=\"concept-title\">Key References</div>\n    <p style=\"font-size: 11px; color: rgba(255,255,255,0.6);\">\n        <strong>MIT Bag Model:</strong> Chodos et al., Phys. Rev. D 9, 3471 (1974)<br>\n        <strong>Chiral Condensate:</strong> Iritani et al., Phys. Rev. D 91, 094501 (2015)<br>\n        <strong>String Tension:</strong> FLAG 2024, \u221a\u03c3 = 440 MeV<br>\n        <strong>Einstein-Cartan:</strong> Hehl et al., Rev. Mod. Phys. 48, 393 (1976)<br>\n        <strong>SU(3) Theory:</strong> Georgi, \"Lie Algebras in Particle Physics\" (1999)<br>\n        <strong>Phase Dynamics:</strong> Sakaguchi & Kuramoto, Prog. Theor. Phys. 76, 576 (1986)\n    </p>\n</div>\n"
  },
  "issue_3": {
    "issue": "Chirality Sign Selection",
    "status": "RESOLVED",
    "derived_from_qcd": "|\u03b1| = 2\u03c0/3 (topological)",
    "cosmologically_selected": "sgn(\u03b1) = +1 (R\u2192G\u2192B)",
    "physical_analogy": "Spontaneous magnetization (Ising model)"
  }
}